composio_langgraph/__init__.py
composio_langgraph/provider.py
composio_langgraph/py.typed
composio_langgraph-0.10.7.dist-info/METADATA
composio_langgraph-0.10.7.dist-info/WHEEL
composio_langgraph-0.10.7.dist-info/top_level.txt
composio_langgraph-0.10.7.dist-info/RECORD
