Metadata-Version: 2.4
Name: composio-langgraph
Version: 0.10.7
Summary: Use Composio to get array of tools with LangGraph Agent Workflows.
Home-page: https://github.com/ComposioHQ/composio
Author: composio
Author-email: Composio <tech@composio.dev>
Project-URL: Homepage, https://github.com/ComposioHQ/composio
Classifier: Programming Language :: Python :: 3
Classifier: License :: OSI Approved :: Apache Software License
Classifier: Operating System :: OS Independent
Requires-Python: >=3.9,<4
Requires-Dist: langgraph
Requires-Dist: composio
Dynamic: author
Dynamic: home-page
Dynamic: requires-python
